gravityai/__init__.py
gravityai/gravityai.py
gravityai-0.1.4.post2.dist-info/LICENSE
gravityai-0.1.4.post2.dist-info/METADATA
gravityai-0.1.4.post2.dist-info/WHEEL
gravityai-0.1.4.post2.dist-info/top_level.txt
gravityai-0.1.4.post2.dist-info/RECORD
