Metadata-Version: 2.1
Name: gravityai
Version: 0.1.4.post2
Summary: The gravity-ai.com helper package
Home-page: https://github.com/GravityAI/gravityai
Author: Jon Huss
Author-email: jon@gravity-ai.com
Classifier: Programming Language :: Python :: 3
Classifier: License :: OSI Approved :: MIT License
Classifier: Operating System :: OS Independent
Requires-Python: >=3.7
License-File: LICENSE
